camai_utils/__init__.py
camai_utils/processing/__init__.py
camai_utils/processing/csvs/__init__.py
camai_utils/processing/csvs/csv_extractor.py
camai_utils/processing/csvs/cue_uploads.py
camai_utils/processing/images/__init__.py
camai_utils/processing/images/image_processing.py
camai_utils/processing/pdfs/.ipynb_checkpoints/pdf_extractor-checkpoint.py
camai_utils/processing/pdfs/__init__.py
camai_utils/processing/pdfs/cepheid.py
camai_utils/processing/pdfs/extractor_utils.py
camai_utils/processing/pdfs/field_mappings.py
camai_utils/processing/pdfs/lab_pdf_extraction.py
camai_utils/processing/pdfs/pdf_extractor.py
camai_utils/processing/pdfs/results_processing.py
camai_utils/processing/text/__init__.py
camai_utils/processing/text/data_to_hl7.py
camai_utils/processing/text/hl7_processing.py
camai_utils/processing/text/lab_text_processing.py
camai_utils/processing/text/result_text_parsing.py
camai_utils-0.1.5.dist-info/WHEEL
camai_utils-0.1.5.dist-info/METADATA
camai_utils-0.1.5.dist-info/RECORD
